jumpstarter_driver_sdwire/__init__.py
jumpstarter_driver_sdwire/driver.py
jumpstarter_driver_sdwire/driver_test.py
jumpstarter_driver_sdwire/py.typed
jumpstarter_driver_sdwire-0.7.4.dist-info/METADATA
jumpstarter_driver_sdwire-0.7.4.dist-info/WHEEL
jumpstarter_driver_sdwire-0.7.4.dist-info/entry_points.txt
jumpstarter_driver_sdwire-0.7.4.dist-info/RECORD
