Metadata-Version: 2.4
Name: jumpstarter-driver-sdwire
Version: 0.7.4
Project-URL: Homepage, https://jumpstarter.dev
Project-URL: source_archive, https://github.com/jumpstarter-dev/repo/archive/c5d38de69eadbb8eb0388bcfe3430a679fff0059.zip
Author-email: Nick Cao <ncao@redhat.com>
License-Expression: Apache-2.0
Requires-Python: >=3.11
Requires-Dist: jumpstarter-driver-opendal==0.7.4
Requires-Dist: jumpstarter==0.7.4
Requires-Dist: pyudev>=0.24.3
Requires-Dist: pyusb>=1.2.1
